LICENSE.txt
README.rst
setup.cfg
setup.py
hdfscontents/__init__.py
hdfscontents/hdfscheckpoints.py
hdfscontents/hdfsio.py
hdfscontents/hdfsmanager.py
hdfscontents.egg-info/PKG-INFO
hdfscontents.egg-info/SOURCES.txt
hdfscontents.egg-info/dependency_links.txt
hdfscontents.egg-info/requires.txt
hdfscontents.egg-info/top_level.txt
tests/__init__.py
tests/runall.py